Metadata-Version: 2.1
Name: pycinema
Version: 3.2.0
Summary: Cinema scientific toolset.
Home-page: https://github.com/cinemascience/pycinema
Author: David H. Rogers
Author-email: dhr@lanl.gov
Classifier: Programming Language :: Python :: 3
Classifier: License :: OSI Approved :: BSD License
Classifier: Operating System :: OS Independent
Requires-Dist: numpy<2.0.0
Requires-Dist: scipy==1.13.1
Requires-Dist: h5py
Requires-Dist: dsi-workflow
Requires-Dist: matplotlib
Requires-Dist: py
Requires-Dist: Pillow
Requires-Dist: moderngl
Requires-Dist: opencv-python-headless
Requires-Dist: ipycanvas
Requires-Dist: ipywidgets
Requires-Dist: PySide6
Requires-Dist: igraph
Requires-Dist: requests
Requires-Dist: pyqtgraph
Requires-Dist: tensorflow
Requires-Dist: trame
Requires-Dist: trame-vuetify
Requires-Dist: trame-plotly
Requires-Dist: pandas
Requires-Dist: pyyaml
